face_genius/__init__.py
face_genius/face_genius.py
face_genius/utils.py
face_recognition_demo-0.2.0.dist-info/METADATA
face_recognition_demo-0.2.0.dist-info/WHEEL
face_recognition_demo-0.2.0.dist-info/top_level.txt
face_recognition_demo-0.2.0.dist-info/RECORD
