Metadata-Version: 2.1
Name: face-recognition-demo
Version: 0.2.0
Summary: A simple face recognition example package
Home-page: https://github.com/NeuronsUII/LizaAlert_n
Author: Victor Tkachev
Author-email: vic.tkachev@gmail.com
Classifier: Programming Language :: Python :: 3
Classifier: License :: OSI Approved :: MIT License
Classifier: Operating System :: OS Independent
Requires-Dist: face-recognition
Requires-Dist: numpy
